{ 
    "_id" : ObjectId("56ef54ceff8db2715e8ef094"), 
    "name" : "Polo", 
    "varient" : [
        {
            "name" : "Trendline 1.2L(P)", 
            "Price" : "5.33 Lac", 
            "Type" : ""
        }, 
        {
            "name" : "Comfortline 1.2L(P)", 
            "Price" : "6 Lac", 
            "Type" : ""
        }, 
        {
            "name" : "Highline 1.2L(P)", 
            "Price" : "6.87 Lac", 
            "Type" : ""
        },
      {
        "name": "GT TDI",
        "Price": "8.9 Lac",
        "Type": "Diesel",
        "Overview": {
          "Mileage-City": "16.02 kmpl",
          "Mileage-Highway": "19.91 kmpl",
          "Available Colors": "",
          "Fuel Tank Capacity": "45 (Liters)",
          "Seating Capacity": "5",
          "Transmission Type": "Manual",
          "Engine Displacement (cc)": "1498",
          "Finance Available (EMI)": "26590",
          "Insurance": "33666",
          "Service Cost": "8821/yr",
          "Air Conditioner": "Yes",
          "CD Player": "Yes",
          "AntiLock Braking System": "Yes",
          "Power Steering": "Yes",
          "Power Windows ": "Yes",
          "Leather Seats": "No",
          "Central Locking": "Yes"
        },
        "Engine": {
          "Engine Type": "TDI Diesel Engine",
          "Engine Description": "1.5-litre 103.5bhp 16V TDI Diesel Engine",
          "Engine Displacement(cc)": "1498",
          "No of Cylinders": "4",
          "Maxinum Power": "103.5bhp@4400rpm",
          "Maximum Torque": "250Nm@1500-2500rpm",
          "Valves Per Cylinder": "4",
          "Valve Configuration": "DOHC",
          "Fuel Supply System": "Direct Injection",
          "Bore x Stroke": "77 X 80.5 mm",
          "Compression Ratio": "16.5 : 1",
          "Turbo Charger": "Yes",
          "Super Charger": "No"
        },
        "Transmission": {
          "Transmission Type": "Manual",
          "Gear Box": "5 Speed",
          "Drive Type": "FWD"
        },
        "Susupension System": {
          "Front Suspension": "MacPherson Strut",
          "Rear Suspension": "Semi-Independent Trailing Arm"
        },
        "Steering": {
          "Steering Type": "Power",
          "Steering Column": "Tilt & Telescopic",
          "Steering Gear Type": "Rack & Pinion",
          "Turning Radius": "4.97 metres"
        },
        "Brake System": {
          "Front Brake Type": "Disc",
          "Rear Brake Type": "Drum"
        },
        "Performance": {
          "Top Speed": "183.8 kmph",
          "Acceleration (0-100 kmph)": "10.51 Seconds"
        },
        "Fuel": {
          "Mileage-City": "16.02 kmpl",
          "Mileage-Highway": "19.91 kmpl",
          "Fuel Type": "Diesel",
          "Fuel Tank Capacity (Liters)": "45",
          "Emission Norm Compliance": "BS IV"
        },
        "Tyres": {
          "Tyre Size": "185/60 R15",
          "Tyre Type": "Tubeless,Radial",
          "Wheel Size": "-----",
          "Alloy Wheel Size": "15 Inch"
        },
        "Other Specification": {
          "Seating Capacity": "5",
          "No of Doors": "5"
        },
        "Payload and Towing": {
          "Cargo Volume": "280-liters"
        },
        "GENERAL CAR DETAILS": {
          "Country of Assembly": "India",
          "Country of Manufacture": "India",
          "Introduction Date": "2015-09-07",
          "Warranty Time": "2 Years",
          "Warranty Distance": "Unlimited Kms"
        },
        "COMFORT & CONVENIENCE": {
          "Power Steering": "Yes",
          "Power Windows-Front": "Yes",
          "Power Windows-Rear": "Yes",
          "Automatic Climate Control": "Yes",
          " Air Quality Control": "Yes",
          "Remote Trunk Opener": "Yes",
          "Remote Fuel Lid Opener": "Yes",
          "Low Fuel Warning Light": "Yes",
          "Accessory Power Outlet": "Yes",
          "Trunk Light": "No",
          "Vanity Mirror": "Yes",
          "Rear Reading Lamp": "No",
          "Rear Seat Headrest": "Yes",
          "Rear Seat Centre Arm Rest": "No",
          "Height Adjustable Front Seat Belts": "No",
          "Cup Holders (Front)": "Yes",
          "Cup Holders (Rear)": "No",
          "Rear A/C Vents": "No",
          "Heated Seats (Front)": "No",
          "Heated Seats (Rear)": "No",
          "Seat Lumbar Support": "No",
          "Multifunction Steering": "Yes",
          "Cruise Control": "Yes",
          "Parking Sensors": "Rear",
          "Navigation System": "No",
          "Foldable Rear Seat": "Bench Folding",
          "Smart Access Card Entry": "No",
          "Engine Start/Stop Button": "No",
          "Glove Box Cooling": "Yes",
          "Bottle Holder": "Front Door",
          "Voice Control": "Yes",
          "Steering Wheel Gearshift Paddles": "No"
        },
        "Interior": {
          "Air Conditioner": "Yes",
          "Heater": "Yes",
          "Adjustable Steering Column": "Yes",
          "Tachometer": "Yes",
          "Electronic Multi-Tripmeter": "Yes",
          "Leather Seats": "No",
          "Fabric Upholstery": "Yes",
          "Leather Steering Wheel": "Yes",
          "Glove Compartment": "Yes",
          "Digital Clock": "Yes",
          "Outside Temperature Display": "No",
          "Cigarette Lighter": "No",
          "Digital Odometer": "Yes",
          "Electric Adjustable Seats": "No",
          "Folding Table in The Rear": "No",
          "Driving Experience Control Eco": "No",
          "Height Adjustable Driving Seat": "Yes"
        },
        "Exterior": {
          "Adjustable Headlights": "Yes",
          "Fog Lights (Front)": "Yes",
          "Fog Lights (Rear)": "Yes",
          "Power Adjustable Exterior Rear View Mirror": "Yes",
          "Manually Adjustable Ext Rear View Mirror": "No",
          "Electric Folding Rear View Mirror": "Yes",
          "Rain Sensing Wiper": "No",
          "Rear Window Wiper": "Yes",
          "Rear Window Washer": "Yes",
          "Rear Window Defogger": "Yes",
          "Wheel Covers": "No",
          "Alloy Wheels": "Yes",
          "Power Antenna": "Yes",
          "Tinted Glass": "Yes",
          "Rear Spoiler ": "Yes",
          "Removable/Convertible Top ": "No",
          "Roof Carrier": "No",
          "Sun Roof": "No",
          "Moon Roof": "No",
          "Side Stepper": "No",
          "Outside Rear View Mirror Turn Indicators": "Yes",
          "Integrated Antenna": "No",
          "Chrome Grille": "No",
          "Chrome Garnish": "No",
          "Smoke Headlamps": "Yes",
          "Roof Rail": "No"
        },
        "Entertainment": {
          "Cassette Player": "No",
          "CD Player": "Yes",
          "CD Changer": "No",
          "DVD Player": "No",
          "Radio": "Yes",
          "Audio System Remote Control": "No",
          "Speakers Front": "Yes",
          "Speakers Rear": "Yes",
          "Integrated 2DIN Audio": "Yes",
          "Bluetooth Connectivity": "Yes",
          "USB & Auxiliary Input": "Yes",
          "Touch Screen": "No"
        },
        "Exterior Dimensions": {
          "Length": "3971mm",
          "Width": "1682mm",
          "Height": "1469mm",
          "Ground Clearance": "165mm",
          "Wheel Base": "2469mm",
          "Front Tread": "1460mm",
          "Rear Tread": "1456mm",
          "Kerb Weight": "1148kg",
          "Gross Weight": "1620Kg"
        },
        "Safety Info": {
          "Anti-Lock Braking": "Yes",
          "Brake Assist": "No",
          "Central Locking": "Yes",
          "Power Door Locks": "Yes",
          "Child Safety Locks": "Yes",
          "Anti-Theft Alarm": "No",
          "Driver Airbag": "Yes",
          "Passenger Airbag": "Yes",
          "Side Airbag (Front)": "No",
          "Side Airbag (Rear)": "No",
          "Night Rear View Mirror": "Yes",
          "Passenger Side Rear View Mirror": "Yes",
          "Xenon Headlamps": "No",
          "Halogen Headlamps": "Yes",
          "Rear Seat Belts": "Yes",
          "Seat Belt Warning": "No",
          "Door Ajar Warning": "No",
          "Side Impact Beams": "Yes",
          "Front Impact Beams": "Yes",
          "Traction Control": "No",
          "Adjustable Seats": "Yes",
          "Keyless Entry": "Yes",
          "Tyre Pressure Monitor": "No",
          "Vehicle Stability Control System": "No",
          "Engine Immobilizer": "Yes",
          "Crash Sensor": "Yes",
          "Centrally Mounted Fuel Tank": "Yes",
          "Engine Check Warning": "No",
          "Automatic Headlamps": "No",
          "Clutch Lock": "No",
          "EBD": "No",
          "Follow Me Home Headlamps": "No",
          "Rear Camera": "No",
          "Anti-Theft Device": "Yes"
        }
      }, 
        {
            "name" : "GT TSI", 
            "Price" : "8.9 Lac", 
            "Type" : ""
        }, 
        {
            "name" : "Trendline 1.5L (D)", 
            "Price" : "6.68 Lac", 
            "Type" : ""
        }, 
        {
            "name" : "Highline 1.5L (D)", 
            "Price" : "8.22 Lac", 
            "Type" : ""
        }, 
        {
            "name" : "Comfortline 1.5L(D)", 
            "Price" : "7.55 Lac", 
            "Type" : ""
        }, 
        {
            "name" : "Polo 1.2L MPI Exquisite", 
            "Price" : "6.7 Lac", 
            "Type" : ""
        }, 
        {
            "name" : "Polo 1.5L TDI Exquisite", 
            "Price" : "8.05 Lac", 
            "Type" : ""
        }
    ]
}
{ 
    "_id" : ObjectId("56ef54d9ff8db2715e8ef096"), 
    "name" : "Cross Polo", 
    "varient" : [
        {
            "name" : "1.5 TDI", 
            "Price" : "8.77 Lac", 
            "Type" : ""
        }, 
        {
            "name" : "1.2 MPI", 
            "Price" : "7.48 Lac", 
            "Type" : ""
        }
    ]
}
{ 
    "_id" : ObjectId("56ef54e3ff8db2715e8ef098"), 
    "name" : "Jetta", 
    "varient" : [
        {
            "name" : "Trendline TSI", 
            "Price" : "14.15 Lac", 
            "Type" : ""
        }, 
        {
            "name" : "Trendline TDI", 
            "Price" : "15.32 Lac", 
            "Type" : ""
        }, 
        {
            "name" : "Comfortable TDI", 
            "Price" : "17.24 Lac", 
            "Type" : ""
        }, 
        {
            "name" : "Highline TDI", 
            "Price" : "19.15 Lac", 
            "Type" : ""
        }, 
        {
            "name" : "hline TDI", 
            "Price" : "20.18 Lac", 
            "Type" : ""
        }
    ]
}
{ 
    "_id" : ObjectId("56ef54ebff8db2715e8ef09a"), 
    "name" : "Vento", 
    "varient" : [
        {
            "name" : "1.5 TDI TRENDLINE", 
            "Price" : "9.1 Lac", 
            "Type" : ""
        }, 
        {
            "name" : "1.5 TDI COMFORTLINE", 
            "Price" : "10 Lac", 
            "Type" : ""
        }, 
        {
            "name" : "1.5 TDI HIGHLINE", 
            "Price" : "10.94 Lac", 
            "Type" : ""
        }, 
        {
            "name" : "1.5 TDI COMFORTLINE AT", 
            "Price" : "11.24 Lac", 
            "Type" : ""
        }, 
        {
            "name" : "1.5 TDI HIGHLINE AT", 
            "Price" : "12.13 Lac"
        }, 
        {
            "name" : "1.6 MPI TRENDLINE", 
            "Price" : "7.85 Lac"
        }, 
        {
            "name" : "1.6 MPI COMFORTLINE", 
            "Price" : "8.79 Lac"
        }, 
        {
            "name" : "1.6 MPI HIGHLINE", 
            "Price" : "9.68 Lac"
        }, 
        {
            "name" : "1.2L TSI COMFORTLINE AT", 
            "Price" : "9.87 Lac"
        }, 
        {
            "name" : "1.2 TSI HIGHLINE AT", 
            "Price" : "10.88 Lac"
        }, 
        {
            "name" : "1.6L MPI Highline Plus", 
            "Price" : "9.7 Lac"
        }
    ]
}
{ 
    "_id" : ObjectId("56ef54f4ff8db2715e8ef09c"), 
    "name" : "Bettle", 
    "varient" : [
        {
            "name" : "1.4 TSI", 
            "Price" : "30.25 Lac", 
            "Type" : ""
        }
    ]
}
